riskplot/__init__.py
riskplot/base.py
riskplot/distributions.py
riskplot/globe.py
riskplot/heatmap.py
riskplot/network.py
riskplot/ridge.py
riskplot/surface.py
riskplot/timeseries.py
riskplot/waterfall.py
riskplot-0.3.0.dist-info/licenses/LICENSE
riskplot-0.3.0.dist-info/METADATA
riskplot-0.3.0.dist-info/WHEEL
riskplot-0.3.0.dist-info/top_level.txt
riskplot-0.3.0.dist-info/RECORD
