Metadata-Version: 2.4
Name: riskplot
Version: 0.3.0
Summary: A comprehensive visualization package for risk analysis with ridge plots, heatmaps, waterfall charts, time series tools, and advanced 2D/3D country mapping
Author-email: Owen Dinsmore <owen@yourdomain.com>
License: MIT
Project-URL: Homepage, https://github.com/OwenDinsmore/riskplot
Project-URL: Documentation, https://owendinsmore.github.io/riskplot
Project-URL: Repository, https://github.com/OwenDinsmore/riskplot
Project-URL: Bug Tracker, https://github.com/OwenDinsmore/riskplot/issues
Keywords: visualization,risk,ridge plots,heatmaps,waterfall charts,matplotlib,pandas,finance,timeseries,geographic,country mapping,choropleth,globe visualization,2D maps,3D maps
Classifier: Development Status :: 3 - Alpha
Classifier: Intended Audience :: Financial and Insurance Industry
Classifier: Intended Audience :: Science/Research
Classifier: License :: OSI Approved :: MIT License
Classifier: Operating System :: OS Independent
Classifier: Programming Language :: Python :: 3
Classifier: Programming Language :: Python :: 3.8
Classifier: Programming Language :: Python :: 3.9
Classifier: Programming Language :: Python :: 3.10
Classifier: Programming Language :: Python :: 3.11
Classifier: Topic :: Scientific/Engineering :: Visualization
Classifier: Topic :: Office/Business :: Financial
Requires-Python: >=3.8
License-File: LICENSE
Requires-Dist: matplotlib>=3.5.0
Requires-Dist: pandas>=1.3.0
Requires-Dist: numpy>=1.20.0
Requires-Dist: scipy>=1.7.0
Requires-Dist: plotly>=5.0.0
Requires-Dist: networkx>=2.6.0
Provides-Extra: dev
Requires-Dist: pytest>=6.0; extra == "dev"
Requires-Dist: pytest-cov; extra == "dev"
Requires-Dist: black; extra == "dev"
Requires-Dist: flake8; extra == "dev"
Requires-Dist: mypy; extra == "dev"
Dynamic: license-file
Dynamic: requires-python
